pg_listener/__init__.py
pg_listener/pg_listener.py
pglistener_gonzalo123-1.0.2.dist-info/METADATA
pglistener_gonzalo123-1.0.2.dist-info/WHEEL
pglistener_gonzalo123-1.0.2.dist-info/top_level.txt
pglistener_gonzalo123-1.0.2.dist-info/RECORD
